YTAnalytics.py
YouTubeAnalytics.py
YouTubeAnalytics-0.1.5.dist-info/METADATA
YouTubeAnalytics-0.1.5.dist-info/WHEEL
YouTubeAnalytics-0.1.5.dist-info/top_level.txt
YouTubeAnalytics-0.1.5.dist-info/RECORD
