Metadata-Version: 2.1
Name: YouTubeAnalytics
Version: 0.1.5
Summary: A Python package to fetch video statistics from a YouTube channel
Home-page: https://github.com/takuma029/YouTubeAnalytics
Author: takuma029
Author-email: s2122090@stu.musashino-u.ac.jp
License: UNKNOWN
Project-URL: Bug Tracker, https://github.com/takuma029/YouTubeAnalytics/issues
Platform: UNKNOWN
Classifier: Programming Language :: Python :: 3
Classifier: License :: OSI Approved :: MIT License
Classifier: Operating System :: OS Independent
Requires-Python: >=3.7
Requires-Dist: python-youtube
